juon/__init__.py
juon/json.py
juon/version.py
juon/xmler.py
juon/dictset/__init__.py
juon/dictset/dictset.py
juon/dictset/display.py
juon/dictset/group_by.py
juon/dictset/records.py
juon/errors/__init__.py
juon/errors/base_exception.py
juon/errors/missing_dependency_error.py
juon/errors/node_not_found_error.py
juon/graphs/__init__.py
juon/graphs/common.py
juon/graphs/diablo.py
juon/graphs/graph.py
juon/graphs/graph_traversal.py
juon/graphs/internals.py
juon/utils/__init__.py
juon/utils/lru_index.py
juon-0.1.2.dist-info/LICENSE
juon-0.1.2.dist-info/METADATA
juon-0.1.2.dist-info/NOTICE.md
juon-0.1.2.dist-info/WHEEL
juon-0.1.2.dist-info/top_level.txt
juon-0.1.2.dist-info/RECORD
