Metadata-Version: 2.1
Name: juon
Version: 0.1.2
Summary: Python Graph Library
Home-page: https://github.com/joocer/juon
Author: joocer
Author-email: justin.joyce@joocer.com
Maintainer: Joocer
License: UNKNOWN
Platform: UNKNOWN
License-File: LICENSE
License-File: NOTICE.md
Requires-Dist: orjson
Requires-Dist: pydantic
